markitdown_cosense/__init__.py
markitdown_cosense/_plugin.py
markitdown_cosense/parser.py
markitdown_cosense/renderer.py
markitdown_cosense-0.2.0.dist-info/licenses/LICENSE
markitdown_cosense-0.2.0.dist-info/METADATA
markitdown_cosense-0.2.0.dist-info/WHEEL
markitdown_cosense-0.2.0.dist-info/entry_points.txt
markitdown_cosense-0.2.0.dist-info/top_level.txt
markitdown_cosense-0.2.0.dist-info/RECORD
