Metadata-Version: 2.4
Name: markitdown-cosense
Version: 0.2.0
Summary: A markitdown plugin for converting Cosense notation to Markdown
Author-email: kazu728 <kazuki.matsuo.728@gmail.com>
License: MIT
Project-URL: Homepage, https://github.com/kazu728/markitdown-cosense
Project-URL: Repository, https://github.com/kazu728/markitdown-cosense
Project-URL: Issues, https://github.com/kazu728/markitdown-cosense/issues
Keywords: markitdown,cosense,markdown,converter,plugin
Classifier: Development Status :: 3 - Alpha
Classifier: Intended Audience :: Developers
Classifier: License :: OSI Approved :: MIT License
Classifier: Programming Language :: Python :: 3
Classifier: Programming Language :: Python :: 3.10
Classifier: Programming Language :: Python :: 3.11
Classifier: Programming Language :: Python :: 3.12
Requires-Python: >=3.10
License-File: LICENSE
Requires-Dist: markitdown>=0.1.1
Provides-Extra: dev
Requires-Dist: pytest>=8.3.5; extra == "dev"
Requires-Dist: pytest-cov>=4.0.0; extra == "dev"
Requires-Dist: ruff>=0.11.12; extra == "dev"
Requires-Dist: pyright>=1.1.390; extra == "dev"
Dynamic: license-file
